dapcy/__init__.py
dapcy/dapc.py
dapcy/geno2csr.py
dapcy/kmean_group.py
dapcy/pca_plot.py
dapcy-1.3.1.dist-info/licenses/LICENSE
dapcy-1.3.1.dist-info/METADATA
dapcy-1.3.1.dist-info/WHEEL
dapcy-1.3.1.dist-info/top_level.txt
dapcy-1.3.1.dist-info/RECORD
