Metadata-Version: 2.4
Name: dapcy
Version: 1.3.1
Summary: An sklearn implementation of discriminant analysis of principal components (DAPC) for population genetics
Author-email: Alejandro Correa Rojo <alejandro.correarojo@uhasselt.be>, Pieter Moris <pmoris@itg.be>
License-Expression: MIT
Project-URL: Homepage, https://gitlab.com/uhasselt-bioinfo/dapcy
Project-URL: Documentation, https://uhasselt-bioinfo.gitlab.io/dapcy/
Project-URL: Repository, https://gitlab.com/uhasselt-bioinfo/dapcy.git
Project-URL: Changelog, https://gitlab.com/uhasselt-bioinfo/dapcy/-/blob/main/CHANGELOG.md
Classifier: Operating System :: OS Independent
Classifier: Programming Language :: Python :: 3
Requires-Python: >=3.6
License-File: LICENSE
Requires-Dist: bed-reader
Requires-Dist: bio2zarr[vcf]>=0.1.6
Requires-Dist: joblib
Requires-Dist: matplotlib
Requires-Dist: numpy
Requires-Dist: pandas
Requires-Dist: scikit-learn
Requires-Dist: scipy
Requires-Dist: seaborn
Requires-Dist: sgkit
Provides-Extra: dev
Requires-Dist: build; extra == "dev"
Requires-Dist: mkdocs>=1.6.1; extra == "dev"
Requires-Dist: mkdocstrings[python]>=0.27.0; extra == "dev"
Requires-Dist: mkdocs-jupyter==0.25.1; extra == "dev"
Requires-Dist: twine; extra == "dev"
Dynamic: license-file
